arylibrary/SamMultiply.py
arylibrary/__init__.py
arylibrary-0.6.0.dist-info/METADATA
arylibrary-0.6.0.dist-info/WHEEL
arylibrary-0.6.0.dist-info/top_level.txt
arylibrary-0.6.0.dist-info/RECORD
